{
  "folder": "aMDioY3CLwUCIibC",
  "name": "Frantic",
  "type": "agenda",
  "img": "modules/alienrpg-corerules/images/Panic-Cards/Frantic.png",
  "system": {
    "attributes": {
      "flag": {
        "value": 0,
        "label": "Flag"
      }
    },
    "general": {
      "comment": {
        "value": "<p>Frantic. All skill rolls based on Strength get &ndash;2 dice.</p>",
        "label": "Text"
      }
    },
    "notes": {
      "notes": ""
    }
  },
  "effects": [],
  "flags": {
    "exportSource": {
      "world": "a-cold-one-with-the-boyz",
      "system": "alienrpg",
      "coreVersion": "12.343",
      "systemVersion": "3.2.4"
    }
  },
  "_stats": {
    "coreVersion": "12.343",
    "systemId": "alienrpg",
    "systemVersion": "3.2.4",
    "createdTime": 1753531665184,
    "modifiedTime": 1753531743689,
    "lastModifiedBy": "UdoUZsuUiToXKTmh"
  }
}